log/__init__.py
log/logger.py
modified_logger-1.1.2.dist-info/METADATA
modified_logger-1.1.2.dist-info/WHEEL
modified_logger-1.1.2.dist-info/entry_points.txt
modified_logger-1.1.2.dist-info/RECORD
