Metadata-Version: 2.1
Name: modified-logger
Version: 1.1.2
Summary: Personal logging abstract from python's logging library that fits my needs
Author-Email: James Baker <james.baker@vanderbilt.edu>
License: Apache-2.0
Requires-Python: >=3.8
